{"fname":"open-notebook.commons.mvisani.2023.03","stub":true,"vault":{"fsPath":"vault"},"schemaStub":false,"type":"note","updated":1746823766063,"created":1746823766063,"id":"65vkm0phh7lz9oxkk5hzt1d","desc":"","links":[],"anchors":{},"children":["2uthwqb9xtcmgpdd821e4dr","kypyoyh6fs25q16mhc0w4jr","zj7mozg36lgdmvkyb01rw7i","ltir06xpwairswiznqobvbe","7dxoqlg3l911jll5cnusrvs","yu7xvrvcp8roccqaxcyp74j","w4lyxdidjo3u07a0oifgkfl","l0fc05g2ah4l8pad3st4u6r"],"parent":"w5osd37pmcghmric8oese7u","data":{},"title":"03"}
