{"fname":"open-notebook.commons.pmallard.2023","stub":true,"vault":{"fsPath":"vault"},"schemaStub":false,"type":"note","updated":1759504612861,"created":1759504612861,"id":"khuho09d3ppbi21kbl9wykt","desc":"","links":[],"anchors":{},"children":["xzxgatyqf5sk2q7a3lr91d2","pht0bx85xfkehtlpg3jyce6","4zbsh4k94xl958hjp7e1xxu","9b49puh3v8vw0juio3r5953","jl76ln1sdh0jubnqz5693rc","qw0rverh0vgd7tq3vvl8zje","9dtijxdm1oabehaqmcby6i8","26loofb9u2q9y3vtat191z9","ctelsp63jsubja7aqb5hsxc"],"parent":"d4mcah2xvvg277z8k34u67a","data":{},"title":"2023"}
