{"id":"mskgwpd1435cbrhvaiczis9","title":"2024-11-20","desc":"","updated":1732111249764,"created":1732111165513,"traitIds":["open-notebook-commons-rouchene"],"custom":{},"fname":"open-notebook.commons.rouchene.2024.11.20","type":"note","vault":{"fsPath":"vault"},"contentHash":"a26a2b6e33973bf6a4bbd068f896e4f9","links":[{"type":"wiki","from":{"fname":"open-notebook.commons.rouchene.2024.11.20","id":"mskgwpd1435cbrhvaiczis9","vaultName":"vault"},"value":"projects.commons-public.microcosmics","position":{"start":{"line":17,"column":5,"offset":304},"end":{"line":17,"column":45,"offset":344},"indent":[]},"xvault":false,"sameFile":false,"to":{"fname":"projects.commons-public.microcosmics"}}],"anchors":{"this-is-rimass-commons-lab-daily-open-notebook":{"type":"header","text":"This is Rimas's COMMONS Lab daily Open Notebook.","value":"this-is-rimass-commons-lab-daily-open-notebook","line":12,"column":0,"depth":1},"todo-today":{"type":"header","text":"Todo today","value":"todo-today","line":16,"column":0,"depth":2},"have-a-look-at-the-commons-research-discussion-forum":{"type":"header","text":"Have a look at the COMMONS research discussion forum","value":"have-a-look-at-the-commons-research-discussion-forum","line":20,"column":0,"depth":3},"daily-work-on-the-microcosmics-project":{"type":"header","text":"Daily work on the Microcosmics project","value":"daily-work-on-the-microcosmics-project","line":23,"column":0,"depth":3},"":{"type":"header","text":"","value":"","line":28,"column":0,"depth":3},"-1":{"type":"header","text":"","value":"-1","line":29,"column":0,"depth":3},"doing":{"type":"header","text":"Doing","value":"doing","line":31,"column":0,"depth":2},"paused":{"type":"header","text":"Paused","value":"paused","line":33,"column":0,"depth":2},"done":{"type":"header","text":"Done","value":"done","line":35,"column":0,"depth":2},"notes":{"type":"header","text":"Notes","value":"notes","line":37,"column":0,"depth":2},"todo-tomorrow-one-day--or-never":{"type":"header","text":"Todo tomorrow, one day ... or never","value":"todo-tomorrow-one-day--or-never","line":39,"column":0,"depth":2},"-2":{"type":"header","text":"","value":"-2","line":42,"column":0,"depth":3},"-3":{"type":"header","text":"","value":"-3","line":43,"column":0,"depth":3},"today-i-learned-that":{"type":"header","text":"Today I learned that","value":"today-i-learned-that","line":46,"column":0,"depth":2}},"children":[],"parent":"k7xjmw30nzljcew1r9g1eek","data":{}}
