{"id":"o10kwttunlssxa9nb75la2y","title":"2023-04-25","desc":"","updated":1682487082038,"created":1682487061609,"traitIds":["open-notebook-commons-pmallard"],"custom":{},"fname":"open-notebook.commons.pmallard.2023.04.25","type":"note","vault":{"fsPath":"vault"},"contentHash":"05e7f14ede53f89f234fab07de957d3b","links":[{"type":"wiki","from":{"fname":"open-notebook.commons.pmallard.2023.04.25","id":"o10kwttunlssxa9nb75la2y","vaultName":"vault"},"value":"tags.mapp","alias":"#mapp","position":{"start":{"line":11,"column":86,"offset":362},"end":{"line":11,"column":91,"offset":367},"indent":[]},"xvault":false,"to":{"fname":"tags.mapp"}},{"type":"wiki","from":{"fname":"open-notebook.commons.pmallard.2023.04.25","id":"o10kwttunlssxa9nb75la2y","vaultName":"vault"},"value":"tags.emi","alias":"#emi","position":{"start":{"line":12,"column":86,"offset":458},"end":{"line":12,"column":90,"offset":462},"indent":[]},"xvault":false,"to":{"fname":"tags.emi"}},{"type":"wiki","from":{"fname":"open-notebook.commons.pmallard.2023.04.25","id":"o10kwttunlssxa9nb75la2y","vaultName":"vault"},"value":"tags.commons","alias":"#commons","position":{"start":{"line":28,"column":86,"offset":683},"end":{"line":28,"column":94,"offset":691},"indent":[]},"xvault":false,"to":{"fname":"tags.commons"}},{"type":"wiki","from":{"fname":"open-notebook.commons.pmallard.2023.04.25","id":"o10kwttunlssxa9nb75la2y","vaultName":"vault"},"value":"tags.dbgi","alias":"#dbgi","position":{"start":{"line":28,"column":96,"offset":693},"end":{"line":28,"column":101,"offset":698},"indent":[]},"xvault":false,"to":{"fname":"tags.dbgi"}},{"type":"wiki","from":{"fname":"open-notebook.commons.pmallard.2023.04.25","id":"o10kwttunlssxa9nb75la2y","vaultName":"vault"},"value":"user.Lendita","alias":"@Lendita","position":{"start":{"line":30,"column":1,"offset":702},"end":{"line":30,"column":9,"offset":710},"indent":[]},"xvault":false,"to":{"fname":"user.Lendita"}},{"type":"wiki","from":{"fname":"open-notebook.commons.pmallard.2023.04.25","id":"o10kwttunlssxa9nb75la2y","vaultName":"vault"},"value":"user.oolonek","alias":"@oolonek","position":{"start":{"line":37,"column":1,"offset":892},"end":{"line":37,"column":9,"offset":900},"indent":[]},"xvault":false,"to":{"fname":"user.oolonek"}},{"type":"wiki","from":{"fname":"open-notebook.commons.pmallard.2023.04.25","id":"o10kwttunlssxa9nb75la2y","vaultName":"vault"},"value":"teaching.master.SBL20004.2023","position":{"start":{"line":50,"column":43,"offset":1475},"end":{"line":50,"column":76,"offset":1508},"indent":[]},"xvault":false,"sameFile":false,"to":{"fname":"teaching.master.SBL20004.2023"}}],"anchors":{"this-is-pmass-commons-lab-daily-open-notebook":{"type":"header","text":"This is PMAS's COMMONS Lab daily Open Notebook.","value":"this-is-pmass-commons-lab-daily-open-notebook","line":10,"column":0,"depth":1},"todo-today":{"type":"header","text":"Todo today","value":"todo-today","line":15,"column":0,"depth":2},"doing":{"type":"header","text":"Doing","value":"doing","line":23,"column":0,"depth":2},"customizing-website":{"type":"header","text":"Customizing website","value":"customizing-website","line":25,"column":0,"depth":3},"call-antonio":{"type":"header","text":"Call Antonio","value":"call-antonio","line":29,"column":0,"depth":2},"paused":{"type":"header","text":"Paused","value":"paused","line":35,"column":0,"depth":2},"done":{"type":"header","text":"Done","value":"done","line":59,"column":0,"depth":2},"notes":{"type":"header","text":"Notes","value":"notes","line":64,"column":0,"depth":2},"todo-tomorrow-another-day--or-never-":{"type":"header","text":"Todo tomorrow, another day ... or never !","value":"todo-tomorrow-another-day--or-never-","line":66,"column":0,"depth":2},"":{"type":"header","text":"","value":"","line":67,"column":0,"depth":3},"-1":{"type":"header","text":"","value":"-1","line":68,"column":0,"depth":3},"-2":{"type":"header","text":"","value":"-2","line":69,"column":0,"depth":3},"today-i-learned-that":{"type":"header","text":"Today I learned that","value":"today-i-learned-that","line":71,"column":0,"depth":2}},"children":[],"parent":"f1z7kwcyvla4z1igekd6kbp","data":{}}
