{"fname":"open-notebook.commons.mvisani.2023.03","stub":true,"vault":{"fsPath":"vault"},"schemaStub":false,"type":"note","updated":1751062321098,"created":1751062321098,"id":"w4jaus3539wz84wcmbv97oy","desc":"","links":[],"anchors":{},"children":["2uthwqb9xtcmgpdd821e4dr","kypyoyh6fs25q16mhc0w4jr","zj7mozg36lgdmvkyb01rw7i","ltir06xpwairswiznqobvbe","7dxoqlg3l911jll5cnusrvs","yu7xvrvcp8roccqaxcyp74j","w4lyxdidjo3u07a0oifgkfl","l0fc05g2ah4l8pad3st4u6r"],"parent":"kvk7vja7q8lzylkjhfjo2k1","data":{},"title":"03"}
