{"id":"x8lraffwcr75zzbwtn1isyt","title":"2024-06-14","desc":"","updated":1718633012121,"created":1718350663672,"traitIds":["open-notebook-commons-pamrein"],"custom":{},"fname":"open-notebook.commons.pamrein.2024.06.14","type":"note","vault":{"fsPath":"vault"},"contentHash":"568a62e649d61193198ad12679d2060f","links":[{"type":"wiki","from":{"fname":"open-notebook.commons.pamrein.2024.06.14","id":"x8lraffwcr75zzbwtn1isyt","vaultName":"vault"},"value":"expanded_np_chemspace.abbreviations","position":{"start":{"line":41,"column":1,"offset":1169},"end":{"line":41,"column":43,"offset":1211},"indent":[]},"xvault":false,"sameFile":false,"to":{"fname":"expanded_np_chemspace.abbreviations"}}],"anchors":{"pamreins-daily-open-notebook-commons-lab":{"type":"header","text":"PAMREIN's daily Open Notebook (COMMONS Lab)","value":"pamreins-daily-open-notebook-commons-lab","line":10,"column":0,"depth":1},"todo---check-github":{"type":"header","text":"Todo - Check Github","value":"todo---check-github","line":12,"column":0,"depth":2},"meetings":{"type":"header","text":"Meetings","value":"meetings","line":16,"column":0,"depth":2},"daily-report-what-did-i-learn":{"type":"header","text":"Daily report (What did I learn?)","value":"daily-report-what-did-i-learn","line":20,"column":0,"depth":2},"future-perspective":{"type":"header","text":"Future perspective","value":"future-perspective","line":44,"column":0,"depth":2},"keywords":{"type":"header","text":"Keywords","value":"keywords","line":48,"column":0,"depth":2}},"children":[],"parent":"ps05l8x0patbg34e27gzxv5","data":{}}
